README.rst
setup.py
django_mock_rest/__init__.py
django_mock_rest/admin.py
django_mock_rest/apps.py
django_mock_rest/config.py
django_mock_rest/models.py
django_mock_rest/search.py
django_mock_rest/tests.py
django_mock_rest/urls.py
django_mock_rest/views.py
django_mock_rest.egg-info/PKG-INFO
django_mock_rest.egg-info/SOURCES.txt
django_mock_rest.egg-info/dependency_links.txt
django_mock_rest.egg-info/requires.txt
django_mock_rest.egg-info/top_level.txt
django_mock_rest.egg-info/zip-safe
django_mock_rest/migrations/0001_initial.py
django_mock_rest/migrations/__init__.py