Metadata-Version: 1.1
Name: django-mock-rest
Version: 1.3
Summary: Simple way to create static mock data at rest api endpoints in the Django admin
Home-page: https://github.com/mverleg/django_mock_rest
Author: (the author)
Author-email: mverleg.noreply@gmail.com
License: Revised BSD License (LICENSE.txt)
Keywords: django,mock,test,unit-test,django-admin,rest,rest-api,api,http
Platform: UNKNOWN
Classifier: Development Status :: 5 - Production/Stable
Classifier: Intended Audience :: Developers
Classifier: Natural Language :: English
Classifier: License :: OSI Approved :: BSD License
Classifier: Operating System :: OS Independent
Classifier: Programming Language :: Python
Classifier: Programming Language :: Python :: 3
Classifier: Programming Language :: Python :: 3.4
Classifier: Programming Language :: Python :: 3.5
Classifier: Programming Language :: Python :: 3.6
Classifier: Programming Language :: Python :: 3.7
Classifier: Topic :: Software Development :: Libraries :: Python Modules
